pyella_rs-0.1.5.dist-info/METADATA
pyella_rs-0.1.5.dist-info/WHEEL
ella/types.py
ella/frame.pyi
ella/__init__.pyi
ella/table.py
ella/types.pyi
ella/table.pyi
ella/frame.py
ella/__init__.py
ella/py.typed
ella/_internal.cpython-311-aarch64-linux-gnu.so
pyella_rs-0.1.5.dist-info/RECORD
